opentelemetry/instrumentation/simplerr/__init__.py
opentelemetry/instrumentation/simplerr/package.py
opentelemetry/instrumentation/simplerr/version.py
opentelemetry_instrumentation_simplerr-0.57b0.dist-info/METADATA
opentelemetry_instrumentation_simplerr-0.57b0.dist-info/WHEEL
opentelemetry_instrumentation_simplerr-0.57b0.dist-info/entry_points.txt
opentelemetry_instrumentation_simplerr-0.57b0.dist-info/RECORD
