Metadata-Version: 2.4
Name: opentelemetry-instrumentation-simplerr
Version: 0.57b0
Summary: Simplerr instrumentation for OpenTelemetry
Author-email: "Warren Angelo H. Layson" <warren@wingaru.com.au>
License: Apache-2.0
Classifier: Intended Audience :: Developers
Classifier: License :: OSI Approved :: Apache Software License
Classifier: Programming Language :: Python
Classifier: Programming Language :: Python :: 3
Classifier: Programming Language :: Python :: 3.9
Classifier: Programming Language :: Python :: 3.10
Classifier: Programming Language :: Python :: 3.11
Classifier: Programming Language :: Python :: 3.12
Classifier: Programming Language :: Python :: 3.13
Requires-Python: >=3.6
Requires-Dist: opentelemetry-api~=1.12
Requires-Dist: opentelemetry-instrumentation-wsgi==0.57b0
Requires-Dist: opentelemetry-instrumentation==0.57b0
Requires-Dist: opentelemetry-semantic-conventions==0.57b0
Requires-Dist: opentelemetry-util-http==0.57b0
Provides-Extra: instruments
Requires-Dist: werkzeug<3.0.0; extra == 'instruments'
Provides-Extra: test
Requires-Dist: opentelemetry-test-utils==0.57b0; extra == 'test'
Requires-Dist: werkzeug<3.0.0; extra == 'test'
